schul_cloud_search_tests/__init__.py
schul_cloud_search_tests/proxy.py
schul_cloud_search_tests/stop.py
schul_cloud_search_tests/search/__init__.py
schul_cloud_search_tests/search/__main__.py
schul_cloud_search_tests/search/assertions.py
schul_cloud_search_tests/search/conftest.py
schul_cloud_search_tests/search/server.py
schul_cloud_search_tests/search/test_headers.py
schul_cloud_search_tests/search/test_queries.py
schul_cloud_search_tests/search/test_requests.py
schul_cloud_search_tests/search_tests/__init__.py
schul_cloud_search_tests/search_tests/conftest.py
schul_cloud_search_tests/search_tests/test_links.py
schul_cloud_search_tests/search_tests/test_request.py
schul_cloud_search_tests/search_tests/test_response.py
schul_cloud_search_tests/tests/__init__.py
schul_cloud_search_tests/tests/assertions.py
schul_cloud_search_tests/tests/conftest.py
schul_cloud_search_tests/tests/test_code.py
schul_cloud_search_tests/tests/test_headers.py
schul_cloud_search_tests/tests/test_io.py
schul_cloud_search_tests/tests/test_links.py
schul_cloud_search_tests/tests/test_request.py
schul_cloud_search_tests-1.0.96.dist-info/DESCRIPTION.rst
schul_cloud_search_tests-1.0.96.dist-info/METADATA
schul_cloud_search_tests-1.0.96.dist-info/RECORD
schul_cloud_search_tests-1.0.96.dist-info/WHEEL
schul_cloud_search_tests-1.0.96.dist-info/metadata.json
schul_cloud_search_tests-1.0.96.dist-info/top_level.txt
