Metadata-Version: 2.0
Name: schul-cloud-search-tests
Version: 1.0.96
Summary: Schul-Cloud Search API
Home-page: https://github.com/schul-cloud/schul_cloud_search_tests
Author: UNKNOWN
Author-email: UNKNOWN
License: UNKNOWN
Keywords: Schul-Cloud Search API,Server Tests
Platform: UNKNOWN
Requires-Dist: bottle (==0.12.13)
Requires-Dist: certifi (==2017.4.17)
Requires-Dist: chardet (==3.0.4)
Requires-Dist: click (==6.7)
Requires-Dist: idna (==2.5)
Requires-Dist: jsonschema (==2.6.0)
Requires-Dist: py (==1.4.34)
Requires-Dist: pytest (==3.1.2)
Requires-Dist: python-dateutil (==2.6.0)
Requires-Dist: requests (==2.18.1)
Requires-Dist: schul-cloud-resources-api-v1 (==1.0.0.277)
Requires-Dist: schul-cloud-resources-server-tests (==1.0.260)
Requires-Dist: six (==1.10.0)
Requires-Dist: urllib3 (==1.21.1)
